LICENSE.txt
MANIFEST.in
README.rst
setup.cfg
setup.py
data/data_file
python_clean_logger/__init__.py
python_clean_logger.egg-info/PKG-INFO
python_clean_logger.egg-info/SOURCES.txt
python_clean_logger.egg-info/dependency_links.txt
python_clean_logger.egg-info/entry_points.txt
python_clean_logger.egg-info/requires.txt
python_clean_logger.egg-info/top_level.txt